mayagpt/__init__.py
mayagpt/mayagpt.py
mayagpt/pythonedtor.py
mayagpt/workspace.py
mayagpt-1.0.8.dist-info/LICENSE
mayagpt-1.0.8.dist-info/METADATA
mayagpt-1.0.8.dist-info/WHEEL
mayagpt-1.0.8.dist-info/top_level.txt
mayagpt-1.0.8.dist-info/RECORD
