Metadata-Version: 2.1
Name: mayagpt
Version: 1.0.8
Summary: An AI-powered scripting assistant for Autodesk Maya users! 
Author: Mahmoud Ellithy
Author-email: cmy.mahmoud@hotmail.com
License: MIT
Project-URL: Homepage, https://github.com/MahmoudGFX/mayagpt
License-File: LICENSE
Requires-Dist: setuptools
Requires-Dist: wheel
Requires-Dist: PySide2
Requires-Dist: openai
Requires-Dist: requests
